recbole_cdr/__init__.py
recbole_cdr/config/__init__.py
recbole_cdr/config/configurator.py
recbole_cdr/data/__init__.py
recbole_cdr/data/dataloader.py
recbole_cdr/data/dataset.py
recbole_cdr/data/utils.py
recbole_cdr/dataset_example/ml-100k/ml-100k.inter
recbole_cdr/dataset_example/ml-100k/ml-100k.item
recbole_cdr/dataset_example/ml-100k/ml-100k.user
recbole_cdr/dataset_example/ml-1m/ml-1m.inter
recbole_cdr/dataset_example/ml-1m/ml-1m.item
recbole_cdr/dataset_example/ml-1m/ml-1m.user
recbole_cdr/model/__init__.py
recbole_cdr/model/crossdomain_recommender.py
recbole_cdr/properties/overall.yaml
recbole_cdr/properties/dataset/sample.yaml
recbole_cdr/properties/model/BiTGCF.yaml
recbole_cdr/properties/model/CLFM.yaml
recbole_cdr/properties/model/CMF.yaml
recbole_cdr/properties/model/CoNet.yaml
recbole_cdr/properties/model/DCDCSR.yaml
recbole_cdr/properties/model/DTCDR.yaml
recbole_cdr/properties/model/DeepAPF.yaml
recbole_cdr/properties/model/EMCDR.yaml
recbole_cdr/properties/model/NATR.yaml
recbole_cdr/properties/model/SSCDR.yaml
recbole_cdr/quick_start/__init__.py
recbole_cdr/quick_start/quick_start.py
recbole_cdr/sampler/__init__.py
recbole_cdr/sampler/crossdomain_sampler.py
recbole_cdr/trainer/__init__.py
recbole_cdr/trainer/trainer.py
recbole_cdr/utils/__init__.py
recbole_cdr/utils/enum_type.py
recbole_cdr/utils/utils.py
recbole_cdr-0.1.0.dist-info/LICENSE
recbole_cdr-0.1.0.dist-info/METADATA
recbole_cdr-0.1.0.dist-info/WHEEL
recbole_cdr-0.1.0.dist-info/top_level.txt
recbole_cdr-0.1.0.dist-info/RECORD
