Metadata-Version: 2.1
Name: recbole-cdr
Version: 0.1.0
Summary: A unified, comprehensive and efficient cross-domain-recommendation library
Home-page: https://github.com/RUCAIBox/RecBole-CDR
Author: RecBoleTeam
Author-email: recbole@outlook.com
License: UNKNOWN
Platform: UNKNOWN
Classifier: License :: OSI Approved :: MIT License
Requires-Dist: numpy (>=1.17.2)
Requires-Dist: torch (>=1.7.0)
Requires-Dist: scipy (==1.6.0)
Requires-Dist: pandas (>=1.0.5)
Requires-Dist: tqdm (>=4.48.2)
Requires-Dist: colorlog (==4.7.2)
Requires-Dist: colorama (==0.4.4)
Requires-Dist: scikit-learn (>=0.23.2)
Requires-Dist: pyyaml (>=5.1.0)
Requires-Dist: tensorboard (>=2.5.0)
Requires-Dist: recbole (>=1.0.0)
Provides-Extra: hyperopt
Requires-Dist: hyperopt (>=0.2.4) ; extra == 'hyperopt'
